<?xml version="1.0" encoding="utf-8"?>
<Summaries>
  <System>
    <Enum>
      <Methods>
        <AnnotationType>Predefined</AnnotationType>
        <Annotation>BasicScalarSystemCall</Annotation>
      </Methods>
    </Enum>
    <Environment>
      <Methods>
        <AnnotationType>Predefined</AnnotationType>
        <Annotation>BasicScalarSystemCall</Annotation>
      </Methods>
    </Environment>
    <Console>
      <Methods>
        <AnnotationType>Predefined</AnnotationType>
        <Annotation>BasicScalarSystemCall</Annotation>
      </Methods>
      <Properties>
        <AnnotationType>Predefined</AnnotationType>
        <Annotation>BasicScalarSystemProperty</Annotation>
      </Properties>
    </Console>
    <Object>
      <Methods>
        <ToString>
          <AnnotationType>Custom</AnnotationType>
          <Annotation>Null.{}.{R}.{}.{}</Annotation>
        </ToString>
        <ReferenceEquals>
          <AnnotationType>Custom</AnnotationType>
          <Annotation>Null.{}.{R;P}.{}.{}</Annotation>
        </ReferenceEquals>
        <GetType>
          <AnnotationType>Custom</AnnotationType>
          <Annotation>Fresh.{}.{R}.{RV.?}.{}</Annotation>
        </GetType>
		<Equals>
          <AnnotationType>Custom</AnnotationType>
          <Annotation>Null.{}.{R}.{}.{}</Annotation>
        </Equals>
		<GetHashCode>
          <AnnotationType>Custom</AnnotationType>
          <Annotation>Null.{}.{R}.{}.{}</Annotation>
        </GetHashCode>
      </Methods>
    </Object>
    <String>
      <Methods>
        <AnnotationType>Predefined</AnnotationType>
        <Annotation>BasicScalarSystemCall</Annotation>
        <IsNullOrEmpty>
          <AnnotationType>Custom</AnnotationType>
          <Annotation>Null.{}.{R;P}.{}.{}</Annotation>
        </IsNullOrEmpty>
      </Methods>
    </String>
    <Int32>
      <Methods>
        <AnnotationType>Predefined</AnnotationType>
        <Annotation>BasicScalarSystemCall</Annotation>
      </Methods>
    </Int32>
    <DateTime>
      <Properties>
        <Now>
          <AnnotationType>Custom</AnnotationType>
          <Annotation>Fresh.{}.{}.{}.{}</Annotation>
        </Now>
      </Properties>
      <Methods>
        <Subtract>
          <AnnotationType>Custom</AnnotationType>
          <Annotation>Fresh.{}.{P.?}.{}.{}</Annotation>
        </Subtract>
        <ctor>
          <AnnotationType>Custom</AnnotationType>
          <Annotation>Fresh.{}.{P}.{}.{}</Annotation>
        </ctor>
        <ParseExact>
          <AnnotationType>Custom</AnnotationType>
          <Annotation>Fresh.{}.{P}.{RV.?}.{}</Annotation>
        </ParseExact>
        <op_Subtraction>
          <AnnotationType>Custom</AnnotationType>
          <Annotation>Fresh.{}.{P;P.?}.{RV.?}.{}</Annotation>
        </op_Subtraction>
      </Methods>
    </DateTime>
    <Guid>
      <Methods>
        <ctor>
          <AnnotationType>Custom</AnnotationType>
          <Annotation>Fresh.{}.{}.{RV.?}.{}</Annotation>
        </ctor>
        <NewGuid>
          <AnnotationType>Custom</AnnotationType>
          <Annotation>Fresh.{}.{P}.{RV.?}.{}</Annotation>
        </NewGuid>
        <GetHashCode>
          <AnnotationType>Custom</AnnotationType>
          <Annotation>Null.{}.{R.?}.{}.{}</Annotation>
        </GetHashCode>
        <ToString>
          <AnnotationType>Custom</AnnotationType>
          <Annotation>Null.{}.{R;R.?;P}.{}.{}</Annotation>
        </ToString>
      </Methods>
    </Guid>
    <Math>
      <Methods>
        <AnnotationType>Predefined</AnnotationType>
        <Annotation>BasicScalarSystemCall</Annotation>
      </Methods>
    </Math>
    <Exception>
      <Methods>
        <ctor>
          <AnnotationType>Custom</AnnotationType>
          <Annotation>Fresh.{Many}.{P}.{RV.?;RO.?}.{[RV;RO, RO, ?]}</Annotation>
        </ctor>
      </Methods>
    </Exception>
    <Array>
      <Methods>
        <ctor>
          <AnnotationType>Custom</AnnotationType>
          <Annotation>Fresh.{}.{P}.{RV.?}.{}</Annotation>
        </ctor>
      </Methods>
      <Properties>
        <AnnotationType>Custom</AnnotationType>
        <Annotation>Null.{}.{R.?}.{}.{}</Annotation>
      </Properties>
    </Array>
    <Type>
      <Methods>
        <GetEvent>
          <AnnotationType>Custom</AnnotationType>
          <Annotation>Fresh.{}.{R;R.?;P;P.?}.{RV.?}.{}</Annotation>
        </GetEvent>
        <GetProperties>
          <AnnotationType>Custom</AnnotationType>
          <Annotation>Fresh.{Many{System.Reflection.PropertyInfo}}.{R;R.?}.{RV.?;RO.?}.{[RV, RO, ?]}</Annotation>
        </GetProperties>
        <GetGenericTypeDefinition>
          <AnnotationType>Custom</AnnotationType>
          <Annotation>Fresh.{}.{R;R.?}.{RV.?}.{}</Annotation>
        </GetGenericTypeDefinition>
        <GetGenericArguments>
          <AnnotationType>Custom</AnnotationType>
          <Annotation>Fresh.{Many{System.Type}}.{R;R.?}.{RV.?;RO.?}.{[RV, RO, ?]}</Annotation>
        </GetGenericArguments>
        <MakeGenericType>
          <AnnotationType>Custom</AnnotationType>
          <Annotation>Fresh.{}.{P;P.?;P.?.?}.{RV.?}.{}</Annotation>
        </MakeGenericType>
      </Methods>
    </Type>
    <GC>
      <Methods>
        <AnnotationType>Predefined</AnnotationType>
        <Annotation>Nothing</Annotation>
      </Methods>
    </GC>
    <IComparable>
      <Methods>
        <CompareTo>
          <AnnotationType>Custom</AnnotationType>
          <Annotation>Null.{}.{R;R.?;R.*.?;P;P.?;P.*.?}.{}.{}</Annotation>
        </CompareTo>
      </Methods>
    </IComparable>
    <Activator>
      <Methods>
        <CreateInstance>
          <AnnotationType>Custom</AnnotationType>
          <Annotation>Fresh.{Many}.{P;P.?}.{RV.?;RO.?}.{[RV;RO, RO, ?], [RO, RV, ?]}</Annotation>
        </CreateInstance>
      </Methods>
    </Activator>
    <Nullable>
      <Methods>
        <GetUnderlyingType>
          <AnnotationType>Custom</AnnotationType>
          <Annotation>Fresh.{}.{P;P.?}.{RV.?}.{}</Annotation>
        </GetUnderlyingType>
      </Methods>
    </Nullable>
  </System>
  <System.IO>
    <DirectoryInfo>
      <Methods>
        <ctor>
          <AnnotationType>Custom</AnnotationType>
          <Annotation>Fresh.{}.{P}.{RV.?}.{}</Annotation>
        </ctor>
      </Methods>
    </DirectoryInfo>
    <TextWriter>
      <Methods>
        <WriteLine>
          <AnnotationType>Predefined</AnnotationType>
          <Annotation>BasicScalarSystemCall</Annotation>
        </WriteLine>
      </Methods>
    </TextWriter>
  </System.IO>
  <System.Reflection>
    <Assembly>
      <Methods>
        <GetExecutingAssembly>
          <AnnotationType>Custom</AnnotationType>
          <Annotation>Fresh.{}.{}.{RV.?}.{}</Annotation>
        </GetExecutingAssembly>
      </Methods>
    </Assembly>
    <PropertyInfo>
      <Methods>
        <GetValue>
          <AnnotationType>Custom</AnnotationType>
          <Annotation>IsIn{P.?}.{}.{R;R.?;P.?}.{}.{}</Annotation>
        </GetValue>
      </Methods>
    </PropertyInfo>
    <EventInfo>
      <Methods>
        <AddEventHandler>
          <AnnotationType>Custom</AnnotationType>
          <Annotation>Null.{}.{R;P}.{R.?}.{}</Annotation>
        </AddEventHandler>
      </Methods>
    </EventInfo>
    <ConstructorInfo>
      <Methods>
        <Invoke>
          <AnnotationType>Custom</AnnotationType>
          <!-- It returns the new object by reading the previous one -->
          <Annotation>IsIn{P[1]}.{}.{R;R.?;P[0]}.{}.{}</Annotation>
        </Invoke>
      </Methods>
    </ConstructorInfo>
  </System.Reflection>
  <System.Linq>
    <Enumerable>
      <Methods>
        <Select>
          <AnnotationType>Custom</AnnotationType>
          <Annotation>Fresh.{}.{P}.{RV.?}.{[RV, P, ?]}</Annotation>
        </Select>
        <Count>
          <AnnotationType>Custom</AnnotationType>
          <Annotation>Null.{}.{P.?}.{}.{}</Annotation>
        </Count>
        <Concat>
          <AnnotationType>Predefined</AnnotationType>
          <Annotation>ReadAll_IsIn_Many</Annotation>
        </Concat>
        <Any>
          <AnnotationType>Predefined</AnnotationType>
          <Annotation>ReadAll_IsIn_Many</Annotation>
        </Any>
		<ToArray>
          <AnnotationType>Predefined</AnnotationType>
          <Annotation>ReadAll_IsIn_Many</Annotation>
        </ToArray>
      </Methods>
    </Enumerable>
    <ImmutableArrayExtensions>
      <Methods>
        <Single>
          <AnnotationType>Predefined</AnnotationType>
          <Annotation>ReadAll_IsIn_Many</Annotation>
        </Single>
        <Select>
          <AnnotationType>Predefined</AnnotationType>
          <Annotation>ReadAll_IsIn_Many</Annotation>
        </Select>
		<Where>
          <AnnotationType>Predefined</AnnotationType>
          <Annotation>ReadAll_IsIn_Many</Annotation>
        </Where>
      </Methods>
    </ImmutableArrayExtensions>
  </System.Linq>
  <System.Xml.Linq>
	<XNode>
		<Methods>
			<ToString>
				<AnnotationType>Predefined</AnnotationType>
				<Annotation>ReadAll</Annotation>
			</ToString>
		</Methods>
	</XNode>
	<XElement>
		<Methods>
			<DescendantsAndSelf>
				<AnnotationType>Predefined</AnnotationType>
				<Annotation>ReadAll_IsIn_Many</Annotation>
			</DescendantsAndSelf>
			<Attributes>
				<AnnotationType>Predefined</AnnotationType>
				<Annotation>ReadAll_IsIn_Many</Annotation>
			</Attributes>
		</Methods>
	</XElement>
  </System.Xml.Linq>
  <System.Collections>
    <ArrayList>
      <Methods>
		<Count>
          <AnnotationType>Predefined</AnnotationType>
		  <Annotation>BasicScalarSystemCall</Annotation>
        </Count>
        <GetEnumerator>
          <AnnotationType>Custom</AnnotationType>
          <Annotation>Fresh.{}.{R.?}.{RV.?}.{[RV, R, list]}</Annotation>
        </GetEnumerator>
        <MoveNext>
          <AnnotationType>Custom</AnnotationType>
          <Annotation>Null.{}.{R.?;R.?.?}.{R.?}.{[R, R.*, Current]}</Annotation>
        </MoveNext>
        <ctor>
          <AnnotationType>Custom</AnnotationType>
          <Annotation>Fresh.{Many}.{P}.{RV.?;RO.?}.{[RV, RO, ?]}</Annotation>
        </ctor>
        <Contains>
          <AnnotationType>Predefined</AnnotationType>
		  <Annotation>ReadAll</Annotation>
        </Contains>
      </Methods>
    </ArrayList>
  </System.Collections>
  <System.Collections.Generic>
    <List>
      <Methods>
        <Count>
          <AnnotationType>Predefined</AnnotationType>
		  <Annotation>BasicScalarSystemCall</Annotation>
        </Count>
        <GetEnumerator>
          <AnnotationType>Custom</AnnotationType>
          <Annotation>Fresh.{}.{R.?}.{RV.?}.{[RV, R, list]}</Annotation>
        </GetEnumerator>
        <MoveNext>
          <AnnotationType>Custom</AnnotationType>
          <Annotation>Null.{}.{R.?;R.?.?}.{R.?}.{[R, R.*, Current]}</Annotation>
        </MoveNext>
        <ctor>
          <AnnotationType>Custom</AnnotationType>
          <Annotation>Fresh.{Single{System.Array}}.{P}.{RV.?;RO.?}.{[RV, RO, ?]}</Annotation>
        </ctor>
        <Sort>
          <AnnotationType>Predefined</AnnotationType>
		  <Annotation>WriteThisReadParameters_Null_Null</Annotation>
        </Sort>
      </Methods>
    </List>
    <IList>
      <Methods>
        <GetEnumerator>
          <AnnotationType>Custom</AnnotationType>
          <Annotation>Fresh.{}.{R.?}.{RV.?}.{[RV, R, list]}</Annotation>
        </GetEnumerator>
        <MoveNext>
          <AnnotationType>Custom</AnnotationType>
          <Annotation>Null.{}.{R.?;R.?.?}.{R.?}.{[R, R.*, Current]}</Annotation>
        </MoveNext>
        <Add>
          <AnnotationType>Custom</AnnotationType>
          <Annotation>Null.{}.{R;R.?.?;P}.{R.?;R.?.?}.{[R.?, P, ?]}</Annotation>
        </Add>
      </Methods>
    </IList>
    <HashSet>
      <Methods>
        <ctor>
          <AnnotationType>Custom</AnnotationType>
          <Annotation>Fresh.{Many{|HashSet}}.{P}.{RV.?;RO.?}.{[RV, RO, ?], [RO, P, ?]}</Annotation>
        </ctor>
      </Methods>
    </HashSet>
    <IEnumerable>
      <Methods>
        <ctor>
          <AnnotationType>Custom</AnnotationType>
          <Annotation>Fresh.{}.{P}.{RV.?}.{[RV, P, ?]}</Annotation>
        </ctor>
        <Add>
          <AnnotationType>Custom</AnnotationType>
          <Annotation>Null.{}.{P}.{R.?}.{[R, P, ?]}</Annotation>
        </Add>
      </Methods>
    </IEnumerable>
	<EqualityComparer>
	  <Methods>
        <Equals>
          <AnnotationType>Predefined</AnnotationType>
          <Annotation>ReadAll</Annotation>
        </Equals>
      </Methods>
	</EqualityComparer>
  </System.Collections.Generic>
  <System.Diagnostics>
    <Process>
      <Methods>
        <GetCurrentProcess>
          <AnnotationType>Custom</AnnotationType>
          <Annotation>Fresh.{Many}.{}.{RV.?;RO.?}.{[RV;RO, RO, ?]}</Annotation>
        </GetCurrentProcess>
      </Methods>
    </Process>
    <Debug>
      <Methods>
        <Assert>
          <AnnotationType>Custom</AnnotationType>
          <Annotation>Null.{}.{P}.{}.{}</Annotation>
        </Assert>
      </Methods>
    </Debug>
  </System.Diagnostics>
  <System.Diagnostics.Contracts>
    <Contract>
      <Methods>
        <EndContractBlock>
          <AnnotationType>Predefined</AnnotationType>
          <Annotation>Nothing</Annotation>
        </EndContractBlock>
      </Methods>
    </Contract>
  </System.Diagnostics.Contracts>
  <log4net>
    <ILog>
      <Methods>
        <Info>
          <AnnotationType>Predefined</AnnotationType>
          <Annotation>BasicScalarSystemCall</Annotation>
        </Info>
      </Methods>
    </ILog>
  </log4net>
  <System.Windows.Forms>
    <Application>
      <Methods>
        <EnableVisualStyles>
          <AnnotationType>Custom</AnnotationType>
          <Annotation>Null.{}.{P}.{}.{}</Annotation>
        </EnableVisualStyles>
        <SetCompatibleTextRenderingDefault>
          <AnnotationType>Custom</AnnotationType>
          <Annotation>Null.{}.{P}.{}.{}</Annotation>
        </SetCompatibleTextRenderingDefault>
      </Methods>
    </Application>
  </System.Windows.Forms>
  <System.Drawing>
    <Point>
      <Methods>
        <ctor>
          <AnnotationType>Custom</AnnotationType>
          <Annotation>Fresh.{}.{P}.{RV.?}.{}</Annotation>
        </ctor>
      </Methods>
    </Point>
    <Size>
      <Methods>
        <ctor>
          <AnnotationType>Custom</AnnotationType>
          <Annotation>Fresh.{}.{P}.{RV.?}.{}</Annotation>
        </ctor>
      </Methods>
    </Size>
    <Font>
      <Methods>
        <ctor>
          <AnnotationType>Custom</AnnotationType>
          <Annotation>Fresh.{}.{P}.{RV.?}.{}</Annotation>
        </ctor>
      </Methods>
    </Font>
  </System.Drawing>
  <AutoMapper>
    <Methods>
      <AnnotationType>Predefined</AnnotationType>
      <Annotation>FullHavoc</Annotation>
    </Methods>
  </AutoMapper>
  <Microsoft.CodeAnalysis>
    <DiagnosticBag>
	  <Methods>
	    <ToReadOnlyAndFree>
		  <AnnotationType>Predefined</AnnotationType>
          <Annotation>ReadAll_IsIn_Many</Annotation>
		</ToReadOnlyAndFree>
		<ToReadOnly>
		  <AnnotationType>Predefined</AnnotationType>
          <Annotation>ReadAll_IsIn_Many</Annotation>
		</ToReadOnly>
		<AsEnumerable>
		  <AnnotationType>Predefined</AnnotationType>
          <Annotation>ReadAll_IsIn_Many</Annotation>
		</AsEnumerable>
		<AsEnumerableWithoutResolution>
		  <AnnotationType>Predefined</AnnotationType>
          <Annotation>ReadAll_IsIn_Many</Annotation>
		</AsEnumerableWithoutResolution>
		<Clear>
		  <AnnotationType>Predefined</AnnotationType>
          <Annotation>BasicScalarSystemCall</Annotation>
		</Clear>
		<Free>
		  <AnnotationType>Predefined</AnnotationType>
          <Annotation>BasicScalarSystemCall</Annotation>
		</Free>
		<GetInstance>
		  <AnnotationType>Custom</AnnotationType>
          <Annotation>Fresh.{}.{R}.{RV.?}.{}</Annotation>
		</GetInstance>
	  </Methods>
	</DiagnosticBag>
    <SymbolDisplayFormat>
      <Methods>
        <WithMiscellaneousOptions>
          <AnnotationType>Predefined</AnnotationType>
          <Annotation>ReadAll_IsIn_Many</Annotation>
        </WithMiscellaneousOptions>
        <WithCompilerInternalOptions>
          <AnnotationType>Predefined</AnnotationType>
          <Annotation>ReadAll_IsIn_Many</Annotation>
        </WithCompilerInternalOptions>
        <AddMiscellaneousOptions>
          <AnnotationType>Predefined</AnnotationType>
          <Annotation>ReadAll_IsIn_Many</Annotation>
        </AddMiscellaneousOptions>
      </Methods>
    </SymbolDisplayFormat>
    <SyntaxTree>
      <Methods>
        <GetRoot>
          <AnnotationType>Predefined</AnnotationType>
          <Annotation>ReadAll_IsIn_Many</Annotation>
        </GetRoot>
      </Methods>
    </SyntaxTree>
    <SyntaxNode>
      <Methods>
        <SerializeTo>
          <AnnotationType>Predefined</AnnotationType>
          <Annotation>ReadAll_IsIn_Many</Annotation>
        </SerializeTo>
      </Methods>
    </SyntaxNode>
	<GreenNode>
	  <Methods>
        <GetSlot>
          <AnnotationType>Predefined</AnnotationType>
          <Annotation>ReadAll_IsIn_Many</Annotation>
        </GetSlot>
      </Methods>
	</GreenNode>
	<DiagnosticExtensions>
		<Methods>
			<Verify>
				<AnnotationType>Predefined</AnnotationType>
				<Annotation>ReadAll</Annotation>
			</Verify>
		</Methods>
	</DiagnosticExtensions>
  </Microsoft.CodeAnalysis>
  <Microsoft.CodeAnalysis.CSharp>
    <CSharpParseOptions>
      <Methods>
        <WithKind>
          <AnnotationType>Predefined</AnnotationType>
          <Annotation>ReadAll_IsIn_Many</Annotation>
        </WithKind>
        <WithLanguageVersion>
          <AnnotationType>Predefined</AnnotationType>
          <Annotation>ReadAll_IsIn_Many</Annotation>
        </WithLanguageVersion>
        <WithDocumentationMode>
          <AnnotationType>Predefined</AnnotationType>
          <Annotation>ReadAll_IsIn_Many</Annotation>
        </WithDocumentationMode>
        <WithFeatures>
          <AnnotationType>Predefined</AnnotationType>
          <Annotation>ReadAll_IsIn_Many</Annotation>
        </WithFeatures>
      </Methods>
    </CSharpParseOptions>
    <CSharpCompilationOptions>
      <Methods>
        <WithDebugPlusMode>
          <AnnotationType>Predefined</AnnotationType>
          <Annotation>ReadAll_IsIn_Many</Annotation>
        </WithDebugPlusMode>
        <WithAllowUnsafe>
          <AnnotationType>Predefined</AnnotationType>
          <Annotation>ReadAll_IsIn_Many</Annotation>
        </WithAllowUnsafe>
        <WithStrongNameProvider>
          <AnnotationType>Predefined</AnnotationType>
          <Annotation>ReadAll_IsIn_Many</Annotation>
        </WithStrongNameProvider>
        <WithConcurrentBuild>
          <AnnotationType>Predefined</AnnotationType>
          <Annotation>ReadAll_IsIn_Many</Annotation>
        </WithConcurrentBuild>
      </Methods>
    </CSharpCompilationOptions>
    <CSharpSyntaxNode>
      <Methods>
        <DeserializeFrom>
          <AnnotationType>Predefined</AnnotationType>
          <Annotation>ReadAll_IsIn_Many</Annotation>
        </DeserializeFrom>
      </Methods>
    </CSharpSyntaxNode>
    <Symbol>
      <Methods>
        <ToDisplayString>
          <AnnotationType>Predefined</AnnotationType>
          <Annotation>ReadAll_IsIn_Many</Annotation>
        </ToDisplayString>
      </Methods>
    </Symbol>
  </Microsoft.CodeAnalysis.CSharp>
  <Microsoft.CodeAnalysis.Emit>
    <EmitOptions>
      <Methods>
        <WithDebugInformationFormat>
          <AnnotationType>Predefined</AnnotationType>
          <Annotation>ReadAll_IsIn_Many</Annotation>
        </WithDebugInformationFormat>
      </Methods>
    </EmitOptions>
  </Microsoft.CodeAnalysis.Emit>
  <Microsoft.CodeAnalysis.PooledObjects>
    <ArrayBuilder>
      <Methods>
        <ToImmutableAndFree>
          <AnnotationType>Predefined</AnnotationType>
          <Annotation>ReadAll_IsIn_Many</Annotation>
        </ToImmutableAndFree>
      </Methods>
    </ArrayBuilder>
	<ObjectPool>
	  <Methods>
	    <Allocate>
		  <AnnotationType>Custom</AnnotationType>
          <Annotation>Fresh.{}.{R}.{RV.?}.{}</Annotation>
		</Allocate>
		<Free>
		  <AnnotationType>Predefined</AnnotationType>
          <Annotation>BasicScalarSystemCall</Annotation>
		</Free>
	  </Methods>
	</ObjectPool>
  </Microsoft.CodeAnalysis.PooledObjects>
  <Microsoft.CodeAnalysis.CSharp.Symbols>
    <NamespaceOrTypeSymbol>
      <Methods>
        <GetMembers>
          <AnnotationType>Predefined</AnnotationType>
          <Annotation>ReadAll_IsIn_Many</Annotation>
        </GetMembers>
      </Methods>
    </NamespaceOrTypeSymbol>
    <TypeSymbol>
      <Methods>
        <InterfacesNoUseSiteDiagnostics>
          <AnnotationType>Predefined</AnnotationType>
          <Annotation>ReadAll_IsIn_Many</Annotation>
        </InterfacesNoUseSiteDiagnostics>
        <get_AllInterfacesNoUseSiteDiagnostics>
          <AnnotationType>Predefined</AnnotationType>
          <Annotation>ReadAll_IsIn_Many</Annotation>
        </get_AllInterfacesNoUseSiteDiagnostics>
      </Methods>
    </TypeSymbol>
  </Microsoft.CodeAnalysis.CSharp.Symbols>
  <Roslyn.Test.Utilities>
    <AssertEx>
      <Methods>
        <SetEqual>
          <AnnotationType>Predefined</AnnotationType>
          <Annotation>BasicScalarSystemCall</Annotation>
        </SetEqual>
      </Methods>
    </AssertEx>
    <TargetFrameworkUtil>
      <Methods>
        <GetReferences>
          <AnnotationType>Predefined</AnnotationType>
          <Annotation>ReadAll_IsIn_Many</Annotation>
        </GetReferences>
      </Methods>
    </TargetFrameworkUtil>
	<CustomAssert>
	  <Methods>
        <AnnotationType>Predefined</AnnotationType>
        <Annotation>BasicScalarSystemCall</Annotation>
      </Methods>
	</CustomAssert>
  </Roslyn.Test.Utilities>
  <System.Collections.Immutable>
    <ImmutableArray>
      <Methods>
        <Create>
          <AnnotationType>Predefined</AnnotationType>
          <Annotation>ReadAll_IsIn_Many</Annotation>
        </Create>
      </Methods>
    </ImmutableArray>
  </System.Collections.Immutable>
  <Microsoft.CodeAnalysis.Test.Utilities>
    <PdbValidation>
	  <Methods>
        <VerifyPdb>
		  <AnnotationType>Predefined</AnnotationType>
          <Annotation>ReadAll</Annotation>
		</VerifyPdb>
      </Methods>
	</PdbValidation>
  </Microsoft.CodeAnalysis.Test.Utilities>
  <Xunit>
	<Assert>
		<Methods>
			<NotEqual>
				<AnnotationType>Predefined</AnnotationType>
				<Annotation>ReadAll</Annotation>
			</NotEqual>
		</Methods>
	</Assert>
  </Xunit>
  <Microsoft.DiaSymReader.Tools>
	<PdbToXmlConverter>
		<Methods>
			<ToXml>
				<AnnotationType>Predefined</AnnotationType>
				<Annotation>ReadAll_IsIn_Many</Annotation>
			</ToXml>
		</Methods>
	</PdbToXmlConverter>
  </Microsoft.DiaSymReader.Tools>
  <System.Reflection.Metadata>
	<MetadataReaderProvider>
		<Methods>
			<FromPortablePdbStream>
				<AnnotationType>Predefined</AnnotationType>
				<Annotation>ReadAll_IsIn_Many</Annotation>
			</FromPortablePdbStream>
			<GetMetadataReader>
				<AnnotationType>Predefined</AnnotationType>
				<Annotation>ReadAll_IsIn_Many</Annotation>
			</GetMetadataReader>
		</Methods>
	</MetadataReaderProvider>
	<BlobContentId>
		<Methods>
			<ctor>
				<AnnotationType>Predefined</AnnotationType>
				<Annotation>ReadAll_IsIn_Many</Annotation>
			</ctor>
		</Methods>
	</BlobContentId>
  </System.Reflection.Metadata>
  <System.Reflection.PortableExecutable>
	<PEReader>
		<Methods>
			<ReadPdbChecksumDebugDirectoryData>
				<AnnotationType>Predefined</AnnotationType>
				<Annotation>ReadAll_IsIn_Many</Annotation>
			</ReadPdbChecksumDebugDirectoryData>
		</Methods>
	</PEReader>
  </System.Reflection.PortableExecutable>
  <Roslyn.Utilities>
    <Hash>
	  <Methods>
	    <GetFNVHashCode>
		  <AnnotationType>Predefined</AnnotationType>
          <Annotation>BasicScalarSystemCall</Annotation>
      </GetFNVHashCode>
	  </Methods>
	</Hash>
  </Roslyn.Utilities>
</Summaries>